<?xml version="1.0" encoding="UTF-8"?>

<PropertyList>

  <sim include="Nasal/views.xml">

    <author>BARANGER Emmanuel (3D/FDM)</author>
    <aircraft-version>0.1</aircraft-version>
    <status>Alpha</status>

    <fuel-fraction>0.8</fuel-fraction>

    <startup>
     <splash-texture>Aircraft/SPAD-VII/spadvii-splash.png</splash-texture>
    </startup>

    <systems>
      <electrical>
        <path>Aircraft/j3cub/cub-electrical.xml</path>
      </electrical>
    </systems> 

    <sound>
      <path>Aircraft/SPAD-VII/Sounds/spadvii-sound.xml</path>
    </sound>

    <model>
      <path archive="y">Aircraft/SPAD-VII/Models/spadvii.xml</path>
      <livery>
        <file type="string">default</file>
      </livery>
    </model>

    <submodels> 
      <serviceable type="bool">true</serviceable>
      <path>Aircraft/SPAD-VII/Models/Effects/submodels.xml</path>
    </submodels>

    <multiplay>
      <chat_display>1</chat_display>
      <generic>
        <int type="int">0</int>
        <int type="int">0</int>
        <int type="int">0</int>
        <int type="int">0</int>
        <int type="int">0</int>
        <int type="int">0</int>
      </generic>
    </multiplay>

    <help>
      <title>S.P.A.D. VII</title>
      <key>
        <name>d</name>
        <desc>Open/Close canopy</desc>
      </key>
      <key>
        <name>e</name>
        <desc>Guns fire</desc>
      </key>
    </help>

    <menubar include="Dialogs/spadvii-menu.xml"/>

  </sim>

  <yasim>
    <la5>
      <pilot-lb>180</pilot-lb>
    </la5>
  </yasim>

  <engines>
    <engine>
      <rpm type="double">700</rpm>
    </engine>
  </engines>

  <input>
    <keyboard include="Nasal/spadvii-keyboard.xml"/>
  </input>
 
  <nasal>
    <la5>
      <file>Aircraft/SPAD-VII/Nasal/doors.nas</file>
      <file>Aircraft/SPAD-VII/Nasal/immat.nas</file>
      <file>Aircraft/SPAD-VII/Nasal/liveries.nas</file>
    </la5>
    <guns>
      <file>Aircraft/SPAD-VII/Nasal/weapons.nas</file>
      <file>Aircraft/SPAD-VII/Nasal/revi.nas</file>
    </guns>
  </nasal>

</PropertyList>

